testvault/__init__.py
testvault-0.2.0.dist-info/WHEEL
testvault-0.2.0.dist-info/METADATA
testvault-0.2.0.dist-info/RECORD
